usb4a/__init__.py
usb4a/usb.py
usb4a-0.3.0.dist-info/METADATA
usb4a-0.3.0.dist-info/WHEEL
usb4a-0.3.0.dist-info/top_level.txt
usb4a-0.3.0.dist-info/RECORD
